fluent_input/__init__.py
streamlit_fluent_input-0.0.3.dist-info/METADATA
streamlit_fluent_input-0.0.3.dist-info/WHEEL
streamlit_fluent_input-0.0.3.dist-info/top_level.txt
streamlit_fluent_input-0.0.3.dist-info/RECORD
