Metadata-Version: 2.1
Name: streamlit-fluent-input
Version: 0.0.3
Summary: Streamlit component that uses the Fluent UI to create a Input box.
Home-page: 
Author: Taha Fanaswala
Author-email: tahafanaswala@gmail.com
Requires-Python: >=3.7
Requires-Dist: streamlit >=0.63
Provides-Extra: devel
Requires-Dist: wheel ; extra == 'devel'
Requires-Dist: pytest ==7.4.0 ; extra == 'devel'
Requires-Dist: playwright ==1.39.0 ; extra == 'devel'
Requires-Dist: requests ==2.31.0 ; extra == 'devel'
Requires-Dist: pytest-playwright-snapshot ==1.0 ; extra == 'devel'
Requires-Dist: pytest-rerunfailures ==12.0 ; extra == 'devel'
